biomimetic/PBMOBmc.py
biomimetic/PBOMBmc.py
biomimetic/PMBMOBmc.py
biomimetic/PMBOMBmc.py
biomimetic/PMOBmc.py
biomimetic/POMBmc.py
biomimetic/SBBmc.py
biomimetic/SBmc.py
biomimetic/SMBBmc.py
biomimetic/UBBmc.py
biomimetic/UBmc.py
biomimetic/UMBBmc.py
biomimetic/__init__.py
biomimetic/qbmc/__init__.py
biomimetic/qbmc/adjustments/__init__.py
biomimetic/qbmc/core/__init__.py
biomimetic/qbmc/core/activation copy.py
biomimetic/qbmc/core/activation.py
biomimetic/qbmc/core/learning.py
biomimetic/qbmc/core/preprocessing.py
biomimetic/qbmc/types/__init__.py
biomimetic/qbmc/types/classifier.py
biomimetic/qbmc/types/regressor.py
biomimetic-0.4.7.dist-info/LICENSE
biomimetic-0.4.7.dist-info/METADATA
biomimetic-0.4.7.dist-info/WHEEL
biomimetic-0.4.7.dist-info/top_level.txt
biomimetic-0.4.7.dist-info/RECORD
